odoo8_addon_shopinvader_product_media-8.0.1.0.0.99.dev2-py3.8-nspkg.pth
odoo_addons/shopinvader_product_media/README.rst
odoo_addons/shopinvader_product_media/__init__.py
odoo_addons/shopinvader_product_media/__openerp__.py
odoo_addons/shopinvader_product_media/data/ir_product_export.xml
odoo8_addon_shopinvader_product_media-8.0.1.0.0.99.dev2.dist-info/METADATA
odoo8_addon_shopinvader_product_media-8.0.1.0.0.99.dev2.dist-info/WHEEL
odoo8_addon_shopinvader_product_media-8.0.1.0.0.99.dev2.dist-info/namespace_packages.txt
odoo8_addon_shopinvader_product_media-8.0.1.0.0.99.dev2.dist-info/top_level.txt
odoo8_addon_shopinvader_product_media-8.0.1.0.0.99.dev2.dist-info/RECORD
